exe_kg_lib/__init__.py
exe_kg_lib/classes/__init__.py
exe_kg_lib/classes/data_entity.py
exe_kg_lib/classes/entity.py
exe_kg_lib/classes/exe_kg.py
exe_kg_lib/classes/exe_kg_actors.py
exe_kg_lib/classes/exe_kg_base.py
exe_kg_lib/classes/exe_kg_mixins/__init__.py
exe_kg_lib/classes/exe_kg_mixins/exe_kg_construction_cli_mixin.py
exe_kg_lib/classes/exe_kg_mixins/exe_kg_construction_mixin.py
exe_kg_lib/classes/exe_kg_mixins/exe_kg_edit_mixin.py
exe_kg_lib/classes/exe_kg_mixins/exe_kg_execution_mixin.py
exe_kg_lib/classes/exe_kg_serialization/__init__.py
exe_kg_lib/classes/exe_kg_serialization/data_entity.py
exe_kg_lib/classes/exe_kg_serialization/method.py
exe_kg_lib/classes/exe_kg_serialization/pipeline.py
exe_kg_lib/classes/exe_kg_serialization/task.py
exe_kg_lib/classes/kg_schema.py
exe_kg_lib/classes/method.py
exe_kg_lib/classes/task.py
exe_kg_lib/classes/tasks/README.md
exe_kg_lib/classes/tasks/__init__.py
exe_kg_lib/classes/tasks/ml_tasks.py
exe_kg_lib/classes/tasks/statistic_tasks.py
exe_kg_lib/classes/tasks/visual_tasks.py
exe_kg_lib/cli/__init__.py
exe_kg_lib/cli/main.py
exe_kg_lib/config.py
exe_kg_lib/scripts/__init__.py
exe_kg_lib/scripts/create_task_hierarchy_md.py
exe_kg_lib/shacl/__init__.py
exe_kg_lib/shacl/base_shape_graph_generator.py
exe_kg_lib/shacl/shacl_shape_graph.ttl
exe_kg_lib/utils/__init__.py
exe_kg_lib/utils/cli_utils.py
exe_kg_lib/utils/kg_creation_utils.py
exe_kg_lib/utils/kg_edit_utils.py
exe_kg_lib/utils/kg_validation_utils.py
exe_kg_lib/utils/query_utils.py
exe_kg_lib/utils/string_utils.py
exe_kg_lib/utils/task_utils/__init__.py
exe_kg_lib-2.2.3.dist-info/LICENSE.md
exe_kg_lib-2.2.3.dist-info/METADATA
exe_kg_lib-2.2.3.dist-info/WHEEL
exe_kg_lib-2.2.3.dist-info/RECORD
