Metadata-Version: 2.3
Name: exe-kg-lib
Version: 2.2.3
Summary: Library for executable ML pipelines represented by KGs.
License: AGPL-3.0
Author: Antonis Klironomos
Author-email: antonis.klironomos@de.bosch.com
Maintainer: Antonis Klironomos
Maintainer-email: antonis.klironomos@de.bosch.com
Requires-Python: >=3.8,<4.0
Classifier: Development Status :: 1 - Planning
Classifier: Intended Audience :: Developers
Classifier: Intended Audience :: Science/Research
Classifier: License :: OSI Approved :: GNU Affero General Public License v3
Classifier: Natural Language :: English
Classifier: Programming Language :: Python :: 3
Classifier: Programming Language :: Python :: 3.8
Classifier: Programming Language :: Python :: 3.9
Classifier: Programming Language :: Python :: 3.10
Classifier: Programming Language :: Python :: 3.11
Classifier: Programming Language :: Python :: 3.12
Classifier: Programming Language :: Python :: 3.13
Classifier: Topic :: Scientific/Engineering
Classifier: Topic :: Software Development
Requires-Dist: black[d] (>=22.10,<25.0)
Requires-Dist: matplotlib (>=3.6.2,<4.0.0)
Requires-Dist: mkdocs (>=1.4.2,<2.0.0)
Requires-Dist: pandas
Requires-Dist: pyshacl (>=0.21.0,<0.22.0)
Requires-Dist: rdflib (>=6.2.0,<7.0.0)
Requires-Dist: requests (>=2.32.3,<3.0.0)
Requires-Dist: scikit-learn (>=1.1.3,<2.0.0)
Requires-Dist: typer (>=0.12.3,<0.13.0)
Requires-Dist: typer-cli (>=0.12.3,<0.13.0)
Project-URL: Homepage, https://boschresearch.github.io/ExeKGLib
Project-URL: Repository, https://github.com/boschresearch/ExeKGLib
